randen/__init__.py
randen/data_generator.py
randen-1.0.0.dist-info/LICENSE
randen-1.0.0.dist-info/WHEEL
randen-1.0.0.dist-info/METADATA
randen-1.0.0.dist-info/RECORD
