Metadata-Version: 2.1
Name: randen
Version: 1.0.0
Summary: Random dataframe generator
Home-page: https://github.com/varskann/randen
License: MIT
Keywords: pandas,random,dataframe
Author: Kanishk Varshney
Author-email: varskann1993@gmail.com
Requires-Python: >=3.8,<4.0
Classifier: License :: OSI Approved :: MIT License
Classifier: Programming Language :: Python :: 3
Classifier: Programming Language :: Python :: 3.8
Classifier: Programming Language :: Python :: 3.9
Requires-Dist: Sphinx (>=3.2.1,<4.0.0)
Requires-Dist: numpy (>=1.19.2,<2.0.0)
Requires-Dist: pandas (>=1.1.2,<2.0.0)
Requires-Dist: pylint (>=2.6.0,<3.0.0)
Requires-Dist: pytest (>=6.1.1,<7.0.0)
Requires-Dist: sphinx-rtd-theme (>=0.5.0,<0.6.0)
Requires-Dist: tox (>=3.20.0,<4.0.0)
Project-URL: Repository, https://github.com/varskann/randen
